debiantospdx/__init__.py
debiantospdx/__main__.py
debiantospdx/cli.py
debiantospdx/control_to_dict.py
debiantospdx/deb_spdx.py
debiantospdx/dict_to_tv.py
debiantospdx/make_tv_dict.py
debiantospdx/search.py
debiantospdx/tv_to_dict.py
debiantospdx-0.1.16.dist-info/entry_points.txt
debiantospdx-0.1.16.dist-info/LICENSE
debiantospdx-0.1.16.dist-info/WHEEL
debiantospdx-0.1.16.dist-info/METADATA
debiantospdx-0.1.16.dist-info/RECORD
