Metadata-Version: 2.1
Name: debiantospdx
Version: 0.1.16
Summary: This tool generate SPDX files from your Debian system / packages
Home-page: https://github.com/tk-tanab/debiantospdx
License: Apache-2.0
Author: tk-tanab
Author-email: tk-tanab@ist.osaka-u.ac.jp
Requires-Python: >=3.10,<4.0
Classifier: License :: OSI Approved :: Apache Software License
Classifier: Programming Language :: Python :: 3
Classifier: Programming Language :: Python :: 3.10
Requires-Dist: scancode-toolkit (==31.2.4)
Project-URL: Repository, https://github.com/tk-tanab/debiantospdx
